abstract_melody_parser/__init__.py
abstract_melody_parser/chords.py
abstract_melody_parser/melody.py
abstract_melody_parser/midi_note_queue.py
abstract_melody_parser/rhythm.py
abstract_melody_parser-0.0.2.dist-info/LICENSE
abstract_melody_parser-0.0.2.dist-info/METADATA
abstract_melody_parser-0.0.2.dist-info/WHEEL
abstract_melody_parser-0.0.2.dist-info/top_level.txt
abstract_melody_parser-0.0.2.dist-info/RECORD
