Metadata-Version: 2.1
Name: abstract-melody-parser
Version: 0.0.2
Summary: A python package offering various tools to interpret and parse midi notes.
Home-page: https://https://github.com/FedericoDiMarzo/AbstractMelodyParser
Author: Federico Di Marzo
Author-email: mail.federicodimarzo@gmail.com
License: UNKNOWN
Project-URL: Bug Tracker, https://github.com/FedericoDiMarzo/AbstractMelodyParser/issues
Platform: UNKNOWN
Classifier: Programming Language :: Python :: 3
Classifier: License :: OSI Approved :: MIT License
Classifier: Operating System :: OS Independent
Requires-Python: >=3.6
